perceptron_rust-0.1.3.dist-info/METADATA
perceptron_rust-0.1.3.dist-info/WHEEL
perceptron_rust-0.1.3.dist-info/license_files/LICENSE
perceptron_rust/__init__.py
perceptron_rust/__init__.pyi
perceptron_rust/py.typed
perceptron_rust/perceptron_rust.pypy310-pp73-ppc_64-linux-gnu.so
perceptron_rust-0.1.3.dist-info/RECORD
